lightconfig/__init__.py
lightconfig/lightconfig.py
lightconfig-0.1.3.dist-info/DESCRIPTION.rst
lightconfig-0.1.3.dist-info/METADATA
lightconfig-0.1.3.dist-info/RECORD
lightconfig-0.1.3.dist-info/WHEEL
lightconfig-0.1.3.dist-info/metadata.json
lightconfig-0.1.3.dist-info/top_level.txt
tests/__init__.py
tests/test_lightconfig.py
