Metadata-Version: 2.0
Name: lightconfig
Version: 0.1.3
Summary: LightConfig is a simple library to make user read or write config
Home-page: https://github.com/daassh/LightConfig
Author: zhang xuan
Author-email: testzx@foxmail.com
Maintainer: zhang xuan
Maintainer-email: testzx@foxmail.com
License: MIT License
Platform: all
Classifier: Operating System :: OS Independent
Classifier: Intended Audience :: Developers
Classifier: License :: OSI Approved :: MIT License
Classifier: Programming Language :: Python
Classifier: Programming Language :: Python :: Implementation
Classifier: Programming Language :: Python :: 2
Classifier: Programming Language :: Python :: 2.7
Classifier: Programming Language :: Python :: 3
Classifier: Programming Language :: Python :: 3.4
Classifier: Programming Language :: Python :: 3.5
Classifier: Programming Language :: Python :: 3.6
Classifier: Programming Language :: Python :: 3.7
Classifier: Topic :: Software Development :: Libraries
